pysorting/__init__.py
pysorting/bubblesort.py
pysorting/insertionsort.py
pysorting/quicksort.py
pysorting/shellsort.py
pysorting/utils.py
pysorting-0.1.0.dist-info/LICENSE
pysorting-0.1.0.dist-info/METADATA
pysorting-0.1.0.dist-info/WHEEL
pysorting-0.1.0.dist-info/RECORD
