Metadata-Version: 2.3
Name: pysorting
Version: 0.1.0
Summary: a package to aid user in implementing various sorting algorithms
License: MIT
Author: Chukwunonso Ebele-muolokwu
Requires-Python: >=3.9
Classifier: License :: OSI Approved :: MIT License
Classifier: Programming Language :: Python :: 3
Classifier: Programming Language :: Python :: 3.9
Classifier: Programming Language :: Python :: 3.10
Classifier: Programming Language :: Python :: 3.11
Classifier: Programming Language :: Python :: 3.12
Classifier: Programming Language :: Python :: 3.13
Requires-Dist: tabulate (>=0.9.0,<0.10.0)
